{
  "Project Management": [
    {
      "title": "Google Project Management Certificate",
      "provider": "Coursera",
      "url": "https://www.coursera.org/professional-certificates/google-project-management"
    },
    {
      "title": "Project Management for Beginners",
      "provider": "LinkedIn Learning",
      "url": "https://www.linkedin.com/learning/project-management-foundations"
    }
  ],
  "SQL": [
    {
      "title": "SQL for Data Science",
      "provider": "Coursera",
      "url": "https://www.coursera.org/learn/sql-for-data-science"
    },
    {
      "title": "Intro to SQL",
      "provider": "Khan Academy",
      "url": "https://www.khanacademy.org/computing/computer-programming/sql"
    }
  ],
  "Communication": [
    {
      "title": "Business Communication",
      "provider": "Coursera",
      "url": "https://www.coursera.org/learn/business-communication"
    },
    {
      "title": "Effective Communication",
      "provider": "LinkedIn Learning",
      "url": "https://www.linkedin.com/learning/communication-foundations"
    }
  ]
}